crawler_studio/__init__.py
crawler_studio/config.py
crawler_studio/manage.py
crawler_studio/app_logs/__init__.py
crawler_studio/app_logs/apps.py
crawler_studio/app_logs/models.py
crawler_studio/app_logs/ser.py
crawler_studio/app_logs/urls.py
crawler_studio/app_logs/views.py
crawler_studio/app_logs/migrations/0001_initial.py
crawler_studio/app_logs/migrations/__init__.py
crawler_studio/app_schedule/__init__.py
crawler_studio/app_schedule/admin.py
crawler_studio/app_schedule/apps.py
crawler_studio/app_schedule/models.py
crawler_studio/app_schedule/ser.py
crawler_studio/app_schedule/urls.py
crawler_studio/app_schedule/views.py
crawler_studio/app_schedule/worker.py
crawler_studio/app_schedule/migrations/0001_initial.py
crawler_studio/app_schedule/migrations/__init__.py
crawler_studio/app_scrapyd/__init__.py
crawler_studio/app_scrapyd/admin.py
crawler_studio/app_scrapyd/apps.py
crawler_studio/app_scrapyd/models.py
crawler_studio/app_scrapyd/ser.py
crawler_studio/app_scrapyd/tests.py
crawler_studio/app_scrapyd/urls.py
crawler_studio/app_scrapyd/views.py
crawler_studio/app_scrapyd/migrations/0001_initial.py
crawler_studio/app_scrapyd/migrations/0002_auto_20220624_1644.py
crawler_studio/app_scrapyd/migrations/0003_auto_20220812_1436.py
crawler_studio/app_scrapyd/migrations/0004_auto_20220905_1014.py
crawler_studio/app_scrapyd/migrations/0005_auto_20220923_0112.py
crawler_studio/app_scrapyd/migrations/0006_spiderstartparams.py
crawler_studio/app_scrapyd/migrations/__init__.py
crawler_studio/app_settings/__init__.py
crawler_studio/app_settings/admin.py
crawler_studio/app_settings/apps.py
crawler_studio/app_settings/models.py
crawler_studio/app_settings/ser.py
crawler_studio/app_settings/tests.py
crawler_studio/app_settings/urls.py
crawler_studio/app_settings/views.py
crawler_studio/app_settings/migrations/0001_initial.py
crawler_studio/app_settings/migrations/0002_delete_logserver.py
crawler_studio/app_settings/migrations/__init__.py
crawler_studio/app_user/__init__.py
crawler_studio-1.5.1.dist-info/METADATA
crawler_studio-1.5.1.dist-info/WHEEL
crawler_studio-1.5.1.dist-info/entry_points.txt
crawler_studio-1.5.1.dist-info/top_level.txt
crawler_studio-1.5.1.dist-info/RECORD
